{
  "$schema": "https://raw.githubusercontent.com/getmanfred/mac/v0.3/schema/schema.json",
  "settings": {
    "language": "EN",
    "MACVersion": "0.3"
  },
  "aboutMe": {
    "profile": {
      "name": "Xavier",
      "surnames": "Serrano",
      "title": "Software Engineer 🌍",
      "avatar": {
        "alt": "avatar.jpg",
        "link": "https://media-asgard.s3.eu-west-1.amazonaws.com/22/08/22/82d2a1f0-0207-47dd-bb0e-138626266201_avatar.jpg"
      },
      "location": {
        "notes": "Elche"
      }
    },
    "relevantLinks": [
      {
        "type": "linkedin",
        "URL": "https://www.linkedin.com/in/xsedev/"
      }
    ]
  },
  "experience": {
    "jobs": [
      {
        "organization": {
          "name": "Trazable",
          "image": {
            "alt": "1521195547759.jpeg",
            "link": "https://media-asgard.s3.eu-west-1.amazonaws.com/22/08/23/f8a1d2ac-9802-43fe-859f-055dca884899_1521195547759.jpeg"
          },
          "URL": "https://trazable.io/"
        },
        "roles": [
          {
            "name": " Senior Full Stack Developer",
            "startDate": "2022-03-01",
            "competences": [
              {
                "name": "Google Cloud",
                "type": "technology"
              },
              {
                "name": "MongoDB",
                "type": "technology"
              },
              {
                "name": "NodeJS",
                "type": "technology"
              },
              {
                "name": "React",
                "type": "technology"
              }
            ]
          }
        ]
      }
    ]
  },
  "knowledge": {
    "languages": [
      {
        "name": "English"
      },
      {
        "name": "Spanish"
      }
    ],
    "hardSkills": [
      {
        "skill": {
          "name": "Go",
          "type": "technology"
        }
      },
      {
        "skill": {
          "name": "JavaScript",
          "type": "technology"
        }
      },
      {
        "skill": {
          "name": "NodeJS",
          "type": "technology"
        }
      },
      {
        "skill": {
          "name": "React",
          "type": "technology"
        }
      },
      {
        "skill": {
          "name": "MongoDB",
          "type": "technology"
        }
      },
      {
        "skill": {
          "name": "Kubernetes",
          "type": "technology"
        }
      },
      {
        "skill": {
          "name": "Terraform",
          "type": "technology"
        }
      },
      {
        "skill": {
          "name": "TypeScript",
          "type": "technology"
        }
      }
    ]
  },
  "careerPreferences": {
    "contact": {
      "publicProfiles": [
        {
          "type": "linkedin",
          "URL": "https://www.linkedin.com/in/xsedev/"
        }
      ]
    },
    "preferences": {
      "preferredCompetences": [
        {
          "name": "Go",
          "type": "technology"
        },
        {
          "name": "NodeJS",
          "type": "technology"
        },
        {
          "name": "React",
          "type": "technology"
        },
        {
          "name": "TypeScript",
          "type": "technology"
        }
      ]
    }
  }
}